<?xml version="1.0" encoding="utf-8"?>
<LanguageData>

  <ModSettingsNameMutations>Warhammer 40k - Mutations</ModSettingsNameMutations>

  <baseChanceForGiftOffer>Added chance for pawn being given gift when pawn would recieve a gift: {0}</baseChanceForGiftOffer>
  <maxGiftsWhenGiven>Max amount of gift that can be given at once when pawns receives gift from gods, increasing this will give a chance to receive more gifts up to the set amount. Currently: {0}</maxGiftsWhenGiven>
  <disableDeities>Disables the deity system, this means that you have to find or add the added content yourself.</disableDeities>
  <ticksBetweenGifts>Time range between attempted gift giving</ticksBetweenGifts>
  <mentalBreakMultiplier>Multiplier for favour gained when pawn has a mental breakdown</mentalBreakMultiplier>
  <opinionGainOnGift>Opinion gained with faction upon getting gift from gods which they follow.</opinionGainOnGift>

  <OkChaos>Ok.</OkChaos>

  <ChaosAttraction>{0}'s mental breakdown have attracted {1} attention.
      \n{1} have offered {0} 'solutions' to their problems in exchange for their acceptance of Chaos.</ChaosAttraction>

  <QueryAcceptance>\n\nWill {0} accept this deal, whatever the cost may be...?</QueryAcceptance>

  <TzeentchLetterTitle>The Changer of Ways</TzeentchLetterTitle>
  <KhorneLetterTitle>The Blood God</KhorneLetterTitle>
  <NurgleLetterTitle>The Plague Lord</NurgleLetterTitle>
  <SlaaneshLetterTitle>The Dark Prince</SlaaneshLetterTitle>
  <UndividedLetterTitle>The Great Chaos Undivided</UndividedLetterTitle>
  <NoneLetterTitle>Empty whispers</NoneLetterTitle>

  <GiftLetterMessage>{0} feel the presence of {1} and realize someone heard their plead.</GiftLetterMessage>

  <GiftLetterMessageGiven>\n\nSomething surges through {0}'s body and {0} feels oddly empowered. This feeling is quickly forgotten as they realize something else about them has changed.\n\n{0} has been granted the following gifts:</GiftLetterMessageGiven>

  <MonstrousHands>{0} has monstrous hands</MonstrousHands>

  <Favour>Favour</Favour>
  <TabFavour>Favour</TabFavour>
  <Level>Level</Level>
  <NextLevel>Next level</NextLevel>

  <Forsaken>{0} has forsaken you</Forsaken>
  <Unknown>{0} doesn't care about you</Unknown>

  <CurrentStanding>Current standing: {0}</CurrentStanding>

  <WorshipStandingIgnored>Ignored</WorshipStandingIgnored>
  <WorshipStandingSeen>Interested</WorshipStandingSeen>
  <WorshipStandingAcknowledged>Acknowledged</WorshipStandingAcknowledged>
  <WorshipStandingFavoured>Favoured</WorshipStandingFavoured>
  <WorshipStandingBlessed>Blessed</WorshipStandingBlessed>

  <GodFavour>God Favour</GodFavour>

  <FavourLevel>Current Favour:</FavourLevel>

  <SwitchDeity>Follow {0}</SwitchDeity>
  <StayWithDeity>Keep following {0}</StayWithDeity>

  <SwitchLetterTitle>A shift in religion</SwitchLetterTitle>
  <SwitchLetterMessage>Switching from one deity to another will half your pawns favour with their current god.\n\nDo you wish to follow this new god?</SwitchLetterMessage>

</LanguageData>